LLM_PCT/PCT.py
LLM_PCT/__init__.py
LLM_PCT/constants.py
LLM_PCT/results.py
LLM_PCT-0.0.1.dist-info/AUTHORS.rst
LLM_PCT-0.0.1.dist-info/LICENSE.txt
LLM_PCT-0.0.1.dist-info/METADATA
LLM_PCT-0.0.1.dist-info/WHEEL
LLM_PCT-0.0.1.dist-info/top_level.txt
LLM_PCT-0.0.1.dist-info/RECORD
